CHANGES.txt
LICENSE.txt
MANIFEST.in
README.txt
setup.py
js/__init__.py
js.jquery_ui_multiselect2.egg-info/PKG-INFO
js.jquery_ui_multiselect2.egg-info/SOURCES.txt
js.jquery_ui_multiselect2.egg-info/dependency_links.txt
js.jquery_ui_multiselect2.egg-info/entry_points.txt
js.jquery_ui_multiselect2.egg-info/namespace_packages.txt
js.jquery_ui_multiselect2.egg-info/not-zip-safe
js.jquery_ui_multiselect2.egg-info/requires.txt
js.jquery_ui_multiselect2.egg-info/top_level.txt
js/jquery_ui_multiselect2/__init__.py
js/jquery_ui_multiselect2/test_jquery_ui_multiselect2.txt
js/jquery_ui_multiselect2/resources/css/common.css
js/jquery_ui_multiselect2/resources/css/jquery-multiselect-2.0.css
js/jquery_ui_multiselect2/resources/js/jquery-multiselect-2.0.js
js/jquery_ui_multiselect2/resources/js/locales/jquery-multiselect-2_en.js
js/jquery_ui_multiselect2/resources/js/locales/jquery-multiselect-2_fr.js
js/jquery_ui_multiselect2/resources/js/locales/jquery-multiselect-2_pt.js