Metadata-Version: 1.0
Name: js.jquery-ui-multiselect2
Version: 2.0-rc-2
Summary: Fanstatic packaging of jquery-ui-multiselect2
Home-page: https://github.com/teixas/js.jquery_ui_multiselect2
Author: Fanstatic Developers
Author-email: fanstatic@googlegroups.com
License: BSD
Platform: UNKNOWN
